daggen-0.0.5.dist-info/LICENSE.txt
daggen-0.0.5.dist-info/top_level.txt
daggen-0.0.5.dist-info/RECORD
daggen-0.0.5.dist-info/WHEEL
daggen-0.0.5.dist-info/METADATA
daggen/daggen_commons.h
daggen/common.cpython-310-i386-linux-gnu.so
daggen/common.c
daggen/daggen.c
daggen/dag.pxd
daggen/dag.cpython-310-i386-linux-gnu.so
daggen/common.pxd
daggen/dag.pyx
daggen/__init__.py
daggen/dag.c
daggen/common.pyx
daggen/daggen_commons.c
