Metadata-Version: 2.1
Name: daggen
Version: 0.0.5
Summary: A Python Wrapper for the daggen tool proposed by Frederic Suter
Author-email: Marcos Dias de Assuncao <assuncao@acm.org>
Maintainer-email: Marcos Dias de Assuncao <assuncao@acm.org>
License:                   GNU LESSER GENERAL PUBLIC LICENSE
Project-URL: Homepage, https://github.com/assuncaomarcos/daggen
Project-URL: Bug Reports, https://github.com/assuncaomarcos/daggen/issues
Project-URL: Say Thanks!, https://saythanks.io/to/assuncaomarcos
Project-URL: Source, https://github.com/assuncaomarcos/daggen
Keywords: daggen,generator,graph
Classifier: Development Status :: 3 - Alpha
Classifier: Intended Audience :: Developers
Classifier: Intended Audience :: Information Technology
Classifier: Topic :: Scientific/Engineering
Classifier: Topic :: Software Development :: Libraries
Classifier: License :: OSI Approved :: MIT License
Classifier: Programming Language :: Python :: 3
Classifier: Programming Language :: Python :: 3.7
Classifier: Programming Language :: Python :: 3.8
Classifier: Programming Language :: Python :: 3.9
Classifier: Programming Language :: Python :: 3.10
Classifier: Programming Language :: Python :: 3.11
Classifier: Programming Language :: Python :: 3 :: Only
Requires-Python: <4,>=3.7
Provides-Extra: dev
Provides-Extra: test
License-File: LICENSE.txt
